{"title":"(图论) A. Love Triangle","uid":"eb70c1e0ff89e3aa1306966429c22736","slug":"图论-A-Love-Triangle","date":"2022-10-06T05:24:49.000Z","updated":"2023-09-06T07:13:37.266Z","comments":true,"path":"api/articles/图论-A-Love-Triangle.json","keywords":null,"cover":null,"content":"<p>这个其实是一个很基础的图论题。</p>\n<span id=\"more\"></span>\n\n<p>题目链接：<a href=\"http://codeforces.com/problemset/problem/939/A\">Problem - 939A - Codeforces</a></p>\n<h4 id=\"A-Love-Triangle\"><a href=\"#A-Love-Triangle\" class=\"headerlink\" title=\"A. Love Triangle\"></a>A. Love Triangle</h4><p>As you could know there are no male planes nor female planes. However, each plane on Earth likes some other plane. There are <em>n</em> planes on Earth, numbered from 1 to <em>n</em>, and the plane with number <em>i</em> likes the plane with number <em>f**i</em>, where 1 ≤ <em>f**i</em> ≤ <em>n</em> and <em>f**i</em> ≠ <em>i</em>.</p>\n<p>We call a love triangle a situation in which plane <em>A</em> likes plane <em>B</em>, plane <em>B</em> likes plane <em>C</em> and plane <em>C</em> likes plane <em>A</em>. Find out if there is any love triangle on Earth.</p>\n<p>Input</p>\n<p>The first line contains a single integer <em>n</em> (2 ≤ <em>n</em> ≤ 5000) — the number of planes.</p>\n<p>The second line contains <em>n</em> integers <em>f</em>1, <em>f</em>2, …, <em>f**n</em> (1 ≤ <em>f**i</em> ≤ <em>n</em>, <em>f**i</em> ≠ <em>i</em>), meaning that the <em>i</em>-th plane likes the <em>f**i</em>-th.</p>\n<p>Output</p>\n<p>Output «YES» if there is a love triangle consisting of planes on Earth. Otherwise, output «NO».</p>\n<p>You can output any letter in lower case or in upper case.</p>\n<p>Examples</p>\n<p>input</p>\n<p>Copy</p>\n<div class=\"language-txt\"><button title=\"Copy code\" class=\"copy\"></button><span class=\"lang\">txt</span><pre class=\"shiki material-theme-palenight\" style=\"background-color: #1a1a1a\" tabindex=\"0\"><code><span class=\"line\"><span style=\"color: #babed8\">5</span></span>\n<span class=\"line\"><span style=\"color: #babed8\">2 4 5 1 3</span></span></code></pre></div><p>output</p>\n<p>Copy</p>\n<div class=\"language-txt\"><button title=\"Copy code\" class=\"copy\"></button><span class=\"lang\">txt</span><pre class=\"shiki material-theme-palenight\" style=\"background-color: #1a1a1a\" tabindex=\"0\"><code><span class=\"line\"><span style=\"color: #babed8\">YES</span></span></code></pre></div><p>input</p>\n<p>Copy</p>\n<div class=\"language-txt\"><button title=\"Copy code\" class=\"copy\"></button><span class=\"lang\">txt</span><pre class=\"shiki material-theme-palenight\" style=\"background-color: #1a1a1a\" tabindex=\"0\"><code><span class=\"line\"><span style=\"color: #babed8\">5</span></span>\n<span class=\"line\"><span style=\"color: #babed8\">5 5 5 5 1</span></span></code></pre></div><p>output</p>\n<p>Copy</p>\n<div class=\"language-txt\"><button title=\"Copy code\" class=\"copy\"></button><span class=\"lang\">txt</span><pre class=\"shiki material-theme-palenight\" style=\"background-color: #1a1a1a\" tabindex=\"0\"><code><span class=\"line\"><span style=\"color: #babed8\">NO</span></span></code></pre></div><p>Note</p>\n<p>In first example plane 2 likes plane 4, plane 4 likes plane 1, plane 1 likes plane 2 and that is a love triangle.</p>\n<p>In second example there are no love triangles.</p>\n<p>这个是一个很基础的图论题，只要有f[f[f[i]]] &#x3D;&#x3D; i的话，就说明肯定存在三角关系。</p>\n<p>Python代码:</p>\n<div class=\"language-txt\"><button title=\"Copy code\" class=\"copy\"></button><span class=\"lang\">txt</span><pre class=\"shiki material-theme-palenight\" style=\"background-color: #1a1a1a\" tabindex=\"0\"><code><span class=\"line\"><span style=\"color: #babed8\">n = int(input())</span></span>\n<span class=\"line\"><span style=\"color: #babed8\">f = list(map(int, input().split()))</span></span>\n<span class=\"line\"><span style=\"color: #babed8\">f.insert(0, 0)</span></span>\n<span class=\"line\"><span style=\"color: #babed8\">flag = 0</span></span>\n<span class=\"line\"><span style=\"color: #babed8\">for i in range(1, n + 1):</span></span>\n<span class=\"line\"><span style=\"color: #babed8\">    if f[f[f[i]]] == i:</span></span>\n<span class=\"line\"><span style=\"color: #babed8\">        flag = 1</span></span>\n<span class=\"line\"><span style=\"color: #babed8\">        break</span></span>\n<span class=\"line\"><span style=\"color: #babed8\">if flag:</span></span>\n<span class=\"line\"><span style=\"color: #babed8\">    print(&quot;YES&quot;)</span></span>\n<span class=\"line\"><span style=\"color: #babed8\">else:</span></span>\n<span class=\"line\"><span style=\"color: #babed8\">    print(&quot;NO&quot;)</span></span></code></pre></div>","text":"这个其实是一个很基础的图论题。 题目链接：Problem - 939A - Codeforces A. Love TriangleAs you could kn...","permalink":"/post/图论-A-Love-Triangle","photos":[],"count_time":{"symbolsCount":"1.4k","symbolsTime":"1 mins."},"categories":[],"tags":[{"name":"刷题：图论","slug":"刷题：图论","count":2,"path":"api/tags/刷题：图论.json"}],"toc":"<ol class=\"toc\"><li class=\"toc-item toc-level-4\"><a class=\"toc-link\" href=\"#A-Love-Triangle\"><span class=\"toc-text\">A. Love Triangle</span></a></li></ol>","author":{"name":"Aurora","slug":"blog-author","avatar":"","link":"/","description":"","socials":{"github":"","twitter":"","stackoverflow":"","wechat":"","qq":"","weibo":"","zhihu":"","csdn":"","juejin":"","customs":{}}},"mapped":true,"hidden":false,"prev_post":{"title":"(图论) B.Badge","uid":"2389fbc827cd67eff59dca71550ede06","slug":"图论-B-Badge","date":"2022-10-06T08:32:24.000Z","updated":"2023-09-06T07:13:48.443Z","comments":true,"path":"api/articles/图论-B-Badge.json","keywords":null,"cover":[],"text":"图论+dfs 题目链接：Problem - B - Codeforces B. BadgeIn Summer Informatics School, if a ...","permalink":"/post/图论-B-Badge","photos":[],"count_time":{"symbolsCount":"2.5k","symbolsTime":"2 mins."},"categories":[],"tags":[{"name":"刷题：图论","slug":"刷题：图论","count":2,"path":"api/tags/刷题：图论.json"},{"name":"刷题：DFS","slug":"刷题：DFS","count":1,"path":"api/tags/刷题：DFS.json"}],"author":{"name":"Aurora","slug":"blog-author","avatar":"","link":"/","description":"","socials":{"github":"","twitter":"","stackoverflow":"","wechat":"","qq":"","weibo":"","zhihu":"","csdn":"","juejin":"","customs":{}}}},"next_post":{"title":"(数学)A. Restoring Three Numbers","uid":"1430b8946bb971c1a1aa8572d387e43f","slug":"数学-A-Restoring-Three-Numbers","date":"2022-10-06T03:19:50.000Z","updated":"2023-09-06T07:13:23.178Z","comments":true,"path":"api/articles/数学-A-Restoring-Three-Numbers.json","keywords":null,"cover":null,"text":"这个是一个数学题。不过不必是暴力的。 题目链接：Problem - 1154A - Codeforces A. Restoring Three NumbersP...","permalink":"/post/数学-A-Restoring-Three-Numbers","photos":[],"count_time":{"symbolsCount":"1.5k","symbolsTime":"1 mins."},"categories":[],"tags":[{"name":"刷题：Math","slug":"刷题：Math","count":1,"path":"api/tags/刷题：Math.json"}],"author":{"name":"Aurora","slug":"blog-author","avatar":"","link":"/","description":"","socials":{"github":"","twitter":"","stackoverflow":"","wechat":"","qq":"","weibo":"","zhihu":"","csdn":"","juejin":"","customs":{}}}}}